MANIFEST.in
README.rst
ressl.py
setup.py
ressl.egg-info/PKG-INFO
ressl.egg-info/SOURCES.txt
ressl.egg-info/dependency_links.txt
ressl.egg-info/entry_points.txt
ressl.egg-info/not-zip-safe
ressl.egg-info/requires.txt
ressl.egg-info/top_level.txt