Metadata-Version: 1.0
Name: ressl
Version: 0.2.1
Summary: A SSL redirector for shared hosting environments, e.g. Webfaction
Home-page: http://github.com/jezdez/ressl/
Author: Jannis Leidel
Author-email: jannis@leidel.info
License: BSD
Platform: UNKNOWN
